data_druid/__init__.py
data_druid/structures/__init__.py
data_druid/structures/exceptions.py
data_druid/structures/trees.py
data_druid/tests/__init__.py
data_druid/tests/conftest.py
data_druid/tests/test_folder_tree.py
data_druid-0.1.4.dist-info/LICENSE
data_druid-0.1.4.dist-info/METADATA
data_druid-0.1.4.dist-info/WHEEL
data_druid-0.1.4.dist-info/top_level.txt
data_druid-0.1.4.dist-info/RECORD
